<annotation verified="yes">
    <folder>Annotation</folder>
    <filename>cdMC1189.jpg</filename>
    <path>Annotations-PascalVOC-export/Annotations/cdMC1189.jpg</path>
    <source>
        <database>Unknown</database>
    </source>
    <size>
        <width>256</width>
        <height>256</height>
        <depth>3</depth>
    </size>
    <segmented>0</segmented>
    <object>
    <name>oven</name>
    <pose>Unspecified</pose>
    <truncated>0</truncated>
    <difficult>0</difficult>
    <bndbox>
        <xmin>149.94802701271186</xmin>
        <ymin>74.05198402189265</ymin>
        <xmax>203.46215130649716</xmax>
        <ymax>168.93107786016947</ymax>
    </bndbox>
</object>
</annotation>
